django_htmx_okayjack-3.0.dist-info/licenses/LICENSE
okayjack/__init__.py
okayjack/http.py
okayjack/middleware.py
okayjack/static/okayjack/js/htmx.ext.okayjack.js
django_htmx_okayjack-3.0.dist-info/METADATA
django_htmx_okayjack-3.0.dist-info/WHEEL
django_htmx_okayjack-3.0.dist-info/top_level.txt
django_htmx_okayjack-3.0.dist-info/RECORD
