Metadata-Version: 2.4
Name: django-htmx-okayjack
Version: 3.0
Summary: Tell htmx what to do with success (200) and error (4xx) responses for a request by using new ``hx-*`` attributes.
Home-page: https://github.com/benopotamus/django-htmx-okayjack
Author: Ben Michie
Author-email: benopotamus@tinku.net
License: BSD-2-Clause
Project-URL: Documentation, https://github.com/benopotamus/django-htmx-okayjack/blob/main/README.rst
Project-URL: Release notes, https://github.com/benopotamus/django-htmx-okayjack/blob/main/CHANGELOG.rst
Project-URL: Source, https://github.com/benopotamus/django-htmx-okayjack
Project-URL: Tracker, https://github.com/benopotamus/django-htmx-okayjack/issues
Classifier: Environment :: Web Environment
Classifier: Framework :: Django
Classifier: Framework :: Django :: 4.2
Classifier: Framework :: Django :: 5.0
Classifier: Framework :: Django :: 5.1
Classifier: Framework :: Django :: 5.2
Classifier: Intended Audience :: Developers
Classifier: License :: OSI Approved :: BSD License
Classifier: Operating System :: OS Independent
Classifier: Programming Language :: Python
Classifier: Programming Language :: Python :: 3
Classifier: Programming Language :: Python :: 3 :: Only
Classifier: Programming Language :: Python :: 3.10
Classifier: Programming Language :: Python :: 3.11
Classifier: Programming Language :: Python :: 3.12
Classifier: Programming Language :: Python :: 3.13
Classifier: Topic :: Internet :: WWW/HTTP
Classifier: Topic :: Internet :: WWW/HTTP :: Dynamic Content
Requires-Python: >=3.10
License-File: LICENSE
Requires-Dist: Django>=4.2
Requires-Dist: django-render-block>=0.9.2
Dynamic: license-file
